backuper/__init__.py
backuper/__main__.py
backuper/actions/__init__.py
backuper/actions/abstract.py
backuper/actions/android.py
backuper/actions/backup.py
backuper/actions/compress.py
backuper/actions/reshape.py
backuper/actions/split.py
backuper/config.py
backuper/parameters.py
backuper/runner.py
backuper/utils.py
backuper_nq-0.7.0.dist-info/entry_points.txt
backuper_nq-0.7.0.dist-info/METADATA
backuper_nq-0.7.0.dist-info/WHEEL
backuper_nq-0.7.0.dist-info/RECORD
